stablediffusers/ComposableStableDiffusionXLPipeline.py
stablediffusers/__init__.py
stablediffusers-0.1.dist-info/LICENSE
stablediffusers-0.1.dist-info/METADATA
stablediffusers-0.1.dist-info/WHEEL
stablediffusers-0.1.dist-info/top_level.txt
stablediffusers-0.1.dist-info/RECORD
